Metadata-Version: 2.1
Name: nbtex
Version: 1.0.7
Summary: A light-weight wrapper around LaTeX for mathematical symbols for Jupyter Notebooks
Home-page: https://github.com/narang99/nbtex
Author: Hariom Narang
Author-email: hariom2711@gmail.com
License: UNKNOWN
Platform: UNKNOWN
Classifier: Programming Language :: Python :: 3
Classifier: Operating System :: OS Independent
Classifier: License :: OSI Approved :: MIT License
